cepent/__init__.py
cepent/error.py
cepent/process.py
cepent-0.0.7.dist-info/LICENSE
cepent-0.0.7.dist-info/METADATA
cepent-0.0.7.dist-info/WHEEL
cepent-0.0.7.dist-info/top_level.txt
cepent-0.0.7.dist-info/RECORD
