Metadata-Version: 2.1
Name: cepent
Version: 0.0.7
Summary: Catch error pentaho
Home-page: https://github.com/biwiser-com/cepent
Author: Ysis Longart (Biwiser)
Author-email: ysisl@biwiser.com
License: MIT
Keywords: python,psycopg2,catch,pentaho
Classifier: Development Status :: 1 - Planning
Classifier: Intended Audience :: Developers
Classifier: Programming Language :: Python :: 3
Classifier: Operating System :: Unix
Classifier: Operating System :: MacOS :: MacOS X
Classifier: Operating System :: Microsoft :: Windows
License-File: LICENSE
Requires-Dist: psycopg2
